xlandsat/__init__.py
xlandsat/_composite.py
xlandsat/_enhancement.py
xlandsat/_interpolation.py
xlandsat/_io.py
xlandsat/_pansharpen.py
xlandsat/_version.py
xlandsat/_version_generated.py
xlandsat/datasets.py
xlandsat/tests/__init__.py
xlandsat/tests/test_datasets.py
xlandsat/tests/test_io.py
xlandsat-0.5.0.dist-info/AUTHORS.md
xlandsat-0.5.0.dist-info/LICENSE.txt
xlandsat-0.5.0.dist-info/METADATA
xlandsat-0.5.0.dist-info/WHEEL
xlandsat-0.5.0.dist-info/top_level.txt
xlandsat-0.5.0.dist-info/RECORD
