Metadata-Version: 2.1
Name: xlandsat
Version: 0.5.0
Summary: Analyze Landsat remote sensing images using xarray
Author-email: Leonardo Uieda <leo@uieda.com>
License: MIT License
Project-URL: Documentation, https://www.compgeolab.org/xlandsat
Project-URL: Changelog, https://www.compgeolab.org/xlandsat/latest/changes.html
Project-URL: Bug Tracker, https://github.com/compgeolab/xlandsat/issues
Project-URL: Source Code, https://github.com/compgeolab/xlandsat
Keywords: xarray,remote sensing,satellite,landsat
Classifier: Development Status :: 5 - Production/Stable
Classifier: License :: OSI Approved :: BSD License
Classifier: Operating System :: OS Independent
Classifier: Intended Audience :: Science/Research
Classifier: Intended Audience :: Developers
Classifier: Intended Audience :: Education
Classifier: Topic :: Scientific/Engineering
Classifier: Topic :: Software Development :: Libraries
Classifier: Programming Language :: Python
Classifier: Programming Language :: Python :: 3
Classifier: Programming Language :: Python :: 3.7
Classifier: Programming Language :: Python :: 3.8
Classifier: Programming Language :: Python :: 3.9
Classifier: Programming Language :: Python :: 3.10
Classifier: Programming Language :: Python :: 3.11
Classifier: Programming Language :: Python :: 3.12
Requires-Python: >=3.7
License-File: LICENSE.txt
License-File: AUTHORS.md
Requires-Dist: numpy >=1.19
Requires-Dist: scipy >=1.5
Requires-Dist: xarray >=0.16
Requires-Dist: scikit-image >=0.18
Requires-Dist: pooch >=1.3.0
